{
  "src/routes/+page.css": {
    "file": "_app/immutable/assets/_page-e3b17954.css",
    "src": "src/routes/+page.css"
  },
  ".svelte-kit/generated/nodes/0.js": {
    "file": "_app/immutable/chunks/0-3eb9099c.js",
    "src": ".svelte-kit/generated/nodes/0.js",
    "isDynamicEntry": true,
    "imports": [
      "node_modules/@sveltejs/kit/src/runtime/components/layout.svelte"
    ]
  },
  ".svelte-kit/generated/nodes/1.js": {
    "file": "_app/immutable/chunks/1-f4a12936.js",
    "src": ".svelte-kit/generated/nodes/1.js",
    "isDynamicEntry": true,
    "imports": [
      "node_modules/@sveltejs/kit/src/runtime/components/error.svelte"
    ]
  },
  "_index-fd54fcb0.js": {
    "file": "_app/immutable/chunks/index-fd54fcb0.js",
    "imports": [
      "_index-a109b288.js"
    ]
  },
  ".svelte-kit/generated/nodes/2.js": {
    "file": "_app/immutable/chunks/2-015e0182.js",
    "src": ".svelte-kit/generated/nodes/2.js",
    "isDynamicEntry": true,
    "imports": [
      "src/routes/+page.svelte"
    ]
  },
  "node_modules/@sveltejs/kit/src/runtime/components/layout.svelte": {
    "file": "_app/immutable/components/layout.svelte-fa25d47d.js",
    "src": "node_modules/@sveltejs/kit/src/runtime/components/layout.svelte",
    "isEntry": true,
    "imports": [
      "_index-a109b288.js"
    ]
  },
  "_singletons-8c0ed01e.js": {
    "file": "_app/immutable/chunks/singletons-8c0ed01e.js",
    "imports": [
      "_index-fd54fcb0.js"
    ]
  },
  "node_modules/@sveltejs/kit/src/runtime/components/error.svelte": {
    "file": "_app/immutable/components/error.svelte-b2f45b0d.js",
    "src": "node_modules/@sveltejs/kit/src/runtime/components/error.svelte",
    "isEntry": true,
    "imports": [
      "_index-a109b288.js",
      "_singletons-8c0ed01e.js"
    ]
  },
  "_index-a109b288.js": {
    "file": "_app/immutable/chunks/index-a109b288.js"
  },
  "node_modules/@sveltejs/kit/src/runtime/client/start.js": {
    "file": "_app/immutable/start-9fa27f71.js",
    "src": "node_modules/@sveltejs/kit/src/runtime/client/start.js",
    "isEntry": true,
    "imports": [
      "_index-a109b288.js",
      "_singletons-8c0ed01e.js"
    ],
    "dynamicImports": [
      ".svelte-kit/generated/nodes/0.js",
      ".svelte-kit/generated/nodes/1.js",
      ".svelte-kit/generated/nodes/2.js"
    ]
  },
  "src/routes/+page.svelte": {
    "file": "_app/immutable/components/pages/_page.svelte-267d26db.js",
    "src": "src/routes/+page.svelte",
    "isEntry": true,
    "imports": [
      "_index-a109b288.js",
      "_index-fd54fcb0.js"
    ],
    "css": [
      "_app/immutable/assets/_page-e3b17954.css"
    ]
  }
}